{"giftPurchased":"Gift Purchased","dontHaveEnoughMoney":"You don't have enough money","habitDone":"Habit Done","levelUp":"Level Up","habits":"Habits","gifts":"Gifts","level":"Level","toastTitle":"Good Job!","undo":"Undo","youAlreadyHaveThisCategory":"You already have this category","newCategory":"New Category","errMessage":"An error occurred","save":"Save","name":"Name","newGift":"New Gift","coins":"Coins","priority":"Priority","hardness":"Hardness","isBad":"Is Bad?","newHabit":"New Habit","pleaseEnterName":"Please enter a name","timeInMinute":"Time (in minute)","pleaseEnterNumber":"Please enter a number","valueMustBeLessThan":"Value must be less than","valueMustBeGreaterThan":"Value must be greater than","editHabit":"Edit Habit","appName":"Achievement Box","mostUsed":"Most used","allItems":"All Items","streak":"Streak","topHabit":"Top Habit","times":"Times","topDay":"Top Day","categories":"Categories","coinsBar":"Coins","doSomeHabitsToGatherStatisticsOn":"Do some habits to gather statistics on","darkMode":"Dark Mode","listView":"List View","accentColor":"Accent Color","viewOnGithub":"View on Github","logPage":"Log","archivePage":"Archive","version":"Version","theDatabaseCopiedTo_Downloads/achievement_box":"The database copied to Downloads/achievement_box","backup":"Backup","incorrectFile":"Incorrect file","doYouWantToBackupBeforeRestore":"Do you want to backup before restore?","cancel":"Cancel","settings":"Settings","home":"Home","statistics":"Statistics","log":"Log","smallDailyHabits":"Small daily habits lead to big achievements over time.","EveryStepYouTake":"Every step you take brings you closer to your goal.","ConsistencyIsKey":"Consistency is the key to success; keep going!","BelieveInYourself":"Believe in yourself and all that you are capable of.","CelebrateSmallVictories":"Celebrate every small victory; they add up to great success.","FocusOnProgress":"Focus on progress, not perfection.","YourOnlyLimitIsYourMind":"Your only limit is your mind; think big!","CommitToYourGoals":"Commit to your goals, and they will become your reality.","StayMotivated":"Stay motivated; your hard work will pay off.","EmbraceChallenges":"Embrace challenges; they are opportunities to grow.","StayDisciplined":"Stay disciplined, and success will follow.","EveryHabitYouBuild":"Every habit you build strengthens your path to achievement.","VisualizeYourSuccess":"Visualize your success and work towards it daily.","RememberTheJourney":"Remember, the journey is as important as the destination.","PushYourself":"Push yourself; the results will be worth it.","KeepYourGoalsInSight":"Keep your goals in sight and your determination strong.","YouHaveThePower":"You have the power to create the life you want.","StayPositive":"Stay positive; a positive mindset fuels progress.","DedicateYourselfToYourGoals":"Dedicate yourself to your goals, and they will be within reach.","MakeEachDayCount":"Your achievements are the sum of your daily actions; make each day count.","SmallDailyHabits":"","language":"Language","restore":"Restore","reportErrorInTranslation":"Report Error In Translation"}